design/error_correction.sv
module error_correction (
    input wire [6:0] hamming_recibido,
    input wire [2:0] syndrome,
    input wire error_paridad,

    output wire [6:0] palabra_corregida,
    output wire sec,
    output wire ded
);

    wire syndrome_activo;

    wire corregir_1;
    wire corregir_2;
    wire corregir_3;
    wire corregir_4;
    wire corregir_5;
    wire corregir_6;
    wire corregir_7;

    // ==========================================
    // DETECTAR SI EL SINDROME ES DIFERENTE DE 000
    // ==========================================

    assign syndrome_activo =
        syndrome[2] |
        syndrome[1] |
        syndrome[0];

    // ==========================================
    // SEC
    //
    // Paridad global incorrecta + syndrome != 000
    // ==========================================

    assign sec =
        error_paridad &
        syndrome_activo;

    // ==========================================
    // DED
    //
    // Paridad global correcta + syndrome != 000
    // ==========================================

    assign ded =
        ~error_paridad &
        syndrome_activo;

    // ==========================================
    // CORRECCION DE POSICION 1
    // syndrome = 001
    // ==========================================

    assign corregir_1 =
        sec &
        ~syndrome[2] &
        ~syndrome[1] &
         syndrome[0];

    // ==========================================
    // CORRECCION DE POSICION 2
    // syndrome = 010
    // ==========================================

    assign corregir_2 =
        sec &
        ~syndrome[2] &
         syndrome[1] &
        ~syndrome[0];

    // ==========================================
    // CORRECCION DE POSICION 3
    // syndrome = 011
    // ==========================================

    assign corregir_3 =
        sec &
        ~syndrome[2] &
         syndrome[1] &
         syndrome[0];

    // ==========================================
    // CORRECCION DE POSICION 4
    // syndrome = 100
    // ==========================================

    assign corregir_4 =
        sec &
         syndrome[2] &
        ~syndrome[1] &
        ~syndrome[0];

    // ==========================================
    // CORRECCION DE POSICION 5
    // syndrome = 101
    // ==========================================

    assign corregir_5 =
        sec &
         syndrome[2] &
        ~syndrome[1] &
         syndrome[0];

    // ==========================================
    // CORRECCION DE POSICION 6
    // syndrome = 110
    // ==========================================

    assign corregir_6 =
        sec &
         syndrome[2] &
         syndrome[1] &
        ~syndrome[0];

    // ==========================================
    // CORRECCION DE POSICION 7
    // syndrome = 111
    // ==========================================

    assign corregir_7 =
        sec &
         syndrome[2] &
         syndrome[1] &
         syndrome[0];

    // ==========================================
    // PALABRA CORREGIDA
    // ==========================================

    assign palabra_corregida[0] =
        hamming_recibido[0] ^ corregir_1;

    assign palabra_corregida[1] =
        hamming_recibido[1] ^ corregir_2;

    assign palabra_corregida[2] =
        hamming_recibido[2] ^ corregir_3;

    assign palabra_corregida[3] =
        hamming_recibido[3] ^ corregir_4;

    assign palabra_corregida[4] =
        hamming_recibido[4] ^ corregir_5;

    assign palabra_corregida[5] =
        hamming_recibido[5] ^ corregir_6;

    assign palabra_corregida[6] =
        hamming_recibido[6] ^ corregir_7;

endmodule

EL_3307_Proyecto1_1/sim/tb_error_correction.sv
`timescale 1ns/1ps

module tb_error_correction;

    reg [6:0] hamming_recibido;
    reg [2:0] syndrome;
    reg error_paridad;

    wire [6:0] palabra_corregida;
    wire sec;
    wire ded;

    error_correction dut (
        .hamming_recibido(hamming_recibido),
        .syndrome(syndrome),
        .error_paridad(error_paridad),
        .palabra_corregida(palabra_corregida),
        .sec(sec),
        .ded(ded)
    );

    initial begin

        $dumpfile("error_correction.vcd");
        $dumpvars(0, tb_error_correction);

        $display("");
        $display("============================================================");
        $display("       TESTBENCH - SUBSISTEMA DE CORRECCION SEC-DED");
        $display("============================================================");
        $display("");

        /*
         * ======================================================
         * CASO 1 - SIN ERROR
         * ======================================================
         *
         * Paridad = 0
         * Syndrome = 000
         *
         * No se debe modificar la palabra.
         */

        hamming_recibido = 7'b1010101;
        syndrome = 3'b000;
        error_paridad = 1'b0;

        #10;

        $display("CASO 1 - SIN ERROR");
        $display("  Recibida  : %b", hamming_recibido);
        $display("  Syndrome  : %b", syndrome);
        $display("  Paridad   : %b", error_paridad);
        $display("  Corregida : %b", palabra_corregida);
        $display("  SEC       : %b", sec);
        $display("  DED       : %b", ded);

        if (palabra_corregida == 7'b1010101 &&
            sec == 1'b0 &&
            ded == 1'b0)
            $display("  RESULTADO: OK");
        else
            $display("  RESULTADO: ERROR");

        $display("");


        /*
         * ======================================================
         * CASOS 2-8 - UN ERROR / SEC
         * ======================================================
         *
         * Paridad = 1
         * Syndrome diferente de 000
         *
         * Se debe corregir el bit indicado por el syndrome.
         */


        /*
         * CASO 2 - ERROR EN BIT 1
         * Syndrome = 001
         */

        hamming_recibido = 7'b1010100;
        syndrome = 3'b001;
        error_paridad = 1'b1;

        #10;

        $display("CASO 2 - SEC: ERROR EN BIT 1");
        $display("  Recibida  : %b", hamming_recibido);
        $display("  Syndrome  : %b", syndrome);
        $display("  Paridad   : %b", error_paridad);
        $display("  Corregida : %b", palabra_corregida);
        $display("  SEC       : %b", sec);
        $display("  DED       : %b", ded);

        if (palabra_corregida == 7'b1010101 &&
            sec == 1'b1 &&
            ded == 1'b0)
            $display("  RESULTADO: OK");
        else
            $display("  RESULTADO: ERROR");

        $display("");


        /*
         * CASO 3 - ERROR EN BIT 2
         * Syndrome = 010
         */

        hamming_recibido = 7'b1010111;
        syndrome = 3'b010;
        error_paridad = 1'b1;

        #10;

        $display("CASO 3 - SEC: ERROR EN BIT 2");
        $display("  Recibida  : %b", hamming_recibido);
        $display("  Syndrome  : %b", syndrome);
        $display("  Paridad   : %b", error_paridad);
        $display("  Corregida : %b", palabra_corregida);
        $display("  SEC       : %b", sec);
        $display("  DED       : %b", ded);

        if (palabra_corregida == 7'b1010101 &&
            sec == 1'b1 &&
            ded == 1'b0)
            $display("  RESULTADO: OK");
        else
            $display("  RESULTADO: ERROR");

        $display("");


        /*
         * CASO 4 - ERROR EN BIT 3
         * Syndrome = 011
         */

        hamming_recibido = 7'b1010001;
        syndrome = 3'b011;
        error_paridad = 1'b1;

        #10;

        $display("CASO 4 - SEC: ERROR EN BIT 3");
        $display("  Recibida  : %b", hamming_recibido);
        $display("  Syndrome  : %b", syndrome);
        $display("  Paridad   : %b", error_paridad);
        $display("  Corregida : %b", palabra_corregida);
        $display("  SEC       : %b", sec);
        $display("  DED       : %b", ded);

        if (palabra_corregida == 7'b1010101 &&
            sec == 1'b1 &&
            ded == 1'b0)
            $display("  RESULTADO: OK");
        else
            $display("  RESULTADO: ERROR");

        $display("");


        /*
         * CASO 5 - ERROR EN BIT 4
         * Syndrome = 100
         */

        hamming_recibido = 7'b1011101;
        syndrome = 3'b100;
        error_paridad = 1'b1;

        #10;

        $display("CASO 5 - SEC: ERROR EN BIT 4");
        $display("  Recibida  : %b", hamming_recibido);
        $display("  Syndrome  : %b", syndrome);
        $display("  Paridad   : %b", error_paridad);
        $display("  Corregida : %b", palabra_corregida);
        $display("  SEC       : %b", sec);
        $display("  DED       : %b", ded);

        if (palabra_corregida == 7'b1010101 &&
            sec == 1'b1 &&
            ded == 1'b0)
            $display("  RESULTADO: OK");
        else
            $display("  RESULTADO: ERROR");

        $display("");


        /*
         * CASO 6 - ERROR EN BIT 5
         * Syndrome = 101
         */

        hamming_recibido = 7'b1000101;
        syndrome = 3'b101;
        error_paridad = 1'b1;

        #10;

        $display("CASO 6 - SEC: ERROR EN BIT 5");
        $display("  Recibida  : %b", hamming_recibido);
        $display("  Syndrome  : %b", syndrome);
        $display("  Paridad   : %b", error_paridad);
        $display("  Corregida : %b", palabra_corregida);
        $display("  SEC       : %b", sec);
        $display("  DED       : %b", ded);

        if (palabra_corregida == 7'b1010101 &&
            sec == 1'b1 &&
            ded == 1'b0)
            $display("  RESULTADO: OK");
        else
            $display("  RESULTADO: ERROR");

        $display("");


        /*
         * CASO 7 - ERROR EN BIT 6
         * Syndrome = 110
         */

        hamming_recibido = 7'b1110101;
        syndrome = 3'b110;
        error_paridad = 1'b1;

        #10;

        $display("CASO 7 - SEC: ERROR EN BIT 6");
        $display("  Recibida  : %b", hamming_recibido);
        $display("  Syndrome  : %b", syndrome);
        $display("  Paridad   : %b", error_paridad);
        $display("  Corregida : %b", palabra_corregida);
        $display("  SEC       : %b", sec);
        $display("  DED       : %b", ded);

        if (palabra_corregida == 7'b1010101 &&
            sec == 1'b1 &&
            ded == 1'b0)
            $display("  RESULTADO: OK");
        else
            $display("  RESULTADO: ERROR");

        $display("");


        /*
         * CASO 8 - ERROR EN BIT 7
         * Syndrome = 111
         */

        hamming_recibido = 7'b0010101;
        syndrome = 3'b111;
        error_paridad = 1'b1;

        #10;

        $display("CASO 8 - SEC: ERROR EN BIT 7");
        $display("  Recibida  : %b", hamming_recibido);
        $display("  Syndrome  : %b", syndrome);
        $display("  Paridad   : %b", error_paridad);
        $display("  Corregida : %b", palabra_corregida);
        $display("  SEC       : %b", sec);
        $display("  DED       : %b", ded);

        if (palabra_corregida == 7'b1010101 &&
            sec == 1'b1 &&
            ded == 1'b0)
            $display("  RESULTADO: OK");
        else
            $display("  RESULTADO: ERROR");

        $display("");


        /*
         * ======================================================
         * CASOS 9-15 - DOBLE ERROR / DED
         * ======================================================
         *
         * Paridad = 0
         * Syndrome diferente de 000
         *
         * Se debe detectar DED.
         * La palabra NO se debe modificar.
         */


        /*
         * CASO 9 - DED
         * Syndrome = 001
         */

        hamming_recibido = 7'b1010100;
        syndrome = 3'b001;
        error_paridad = 1'b0;

        #10;

        $display("CASO 9 - DED: SYNDROME 001");
        $display("  Recibida  : %b", hamming_recibido);
        $display("  Syndrome  : %b", syndrome);
        $display("  Paridad   : %b", error_paridad);
        $display("  Corregida : %b", palabra_corregida);
        $display("  SEC       : %b", sec);
        $display("  DED       : %b", ded);

        if (palabra_corregida == hamming_recibido &&
            sec == 1'b0 &&
            ded == 1'b1)
            $display("  RESULTADO: OK");
        else
            $display("  RESULTADO: ERROR");

        $display("");


        /*
         * CASO 10 - DED
         * Syndrome = 010
         */

        hamming_recibido = 7'b1010111;
        syndrome = 3'b010;
        error_paridad = 1'b0;

        #10;

        $display("CASO 10 - DED: SYNDROME 010");
        $display("  Recibida  : %b", hamming_recibido);
        $display("  Syndrome  : %b", syndrome);
        $display("  Paridad   : %b", error_paridad);
        $display("  Corregida : %b", palabra_corregida);
        $display("  SEC       : %b", sec);
        $display("  DED       : %b", ded);

        if (palabra_corregida == hamming_recibido &&
            sec == 1'b0 &&
            ded == 1'b1)
            $display("  RESULTADO: OK");
        else
            $display("  RESULTADO: ERROR");

        $display("");


        /*
         * CASO 11 - DED
         * Syndrome = 011
         */

        hamming_recibido = 7'b1010001;
        syndrome = 3'b011;
        error_paridad = 1'b0;

        #10;

        $display("CASO 11 - DED: SYNDROME 011");
        $display("  Recibida  : %b", hamming_recibido);
        $display("  Syndrome  : %b", syndrome);
        $display("  Paridad   : %b", error_paridad);
        $display("  Corregida : %b", palabra_corregida);
        $display("  SEC       : %b", sec);
        $display("  DED       : %b", ded);

        if (palabra_corregida == hamming_recibido &&
            sec == 1'b0 &&
            ded == 1'b1)
            $display("  RESULTADO: OK");
        else
            $display("  RESULTADO: ERROR");

        $display("");


        /*
         * CASO 12 - DED
         * Syndrome = 100
         */

        hamming_recibido = 7'b1011101;
        syndrome = 3'b100;
        error_paridad = 1'b0;

        #10;

        $display("CASO 12 - DED: SYNDROME 100");
        $display("  Recibida  : %b", hamming_recibido);
        $display("  Syndrome  : %b", syndrome);
        $display("  Paridad   : %b", error_paridad);
        $display("  Corregida : %b", palabra_corregida);
        $display("  SEC       : %b", sec);
        $display("  DED       : %b", ded);

        if (palabra_corregida == hamming_recibido &&
            sec == 1'b0 &&
            ded == 1'b1)
            $display("  RESULTADO: OK");
        else
            $display("  RESULTADO: ERROR");

        $display("");


        /*
         * CASO 13 - DED
         * Syndrome = 101
         */

        hamming_recibido = 7'b1000101;
        syndrome = 3'b101;
        error_paridad = 1'b0;

        #10;

        $display("CASO 13 - DED: SYNDROME 101");
        $display("  Recibida  : %b", hamming_recibido);
        $display("  Syndrome  : %b", syndrome);
        $display("  Paridad   : %b", error_paridad);
        $display("  Corregida : %b", palabra_corregida);
        $display("  SEC       : %b", sec);
        $display("  DED       : %b", ded);

        if (palabra_corregida == hamming_recibido &&
            sec == 1'b0 &&
            ded == 1'b1)
            $display("  RESULTADO: OK");
        else
            $display("  RESULTADO: ERROR");

        $display("");


        /*
         * CASO 14 - DED
         * Syndrome = 110
         */

        hamming_recibido = 7'b1110101;
        syndrome = 3'b110;
        error_paridad = 1'b0;

        #10;

        $display("CASO 14 - DED: SYNDROME 110");
        $display("  Recibida  : %b", hamming_recibido);
        $display("  Syndrome  : %b", syndrome);
        $display("  Paridad   : %b", error_paridad);
        $display("  Corregida : %b", palabra_corregida);
        $display("  SEC       : %b", sec);
        $display("  DED       : %b", ded);

        if (palabra_corregida == hamming_recibido &&
            sec == 1'b0 &&
            ded == 1'b1)
            $display("  RESULTADO: OK");
        else
            $display("  RESULTADO: ERROR");

        $display("");


        /*
         * CASO 15 - DED
         * Syndrome = 111
         */

        hamming_recibido = 7'b0010101;
        syndrome = 3'b111;
        error_paridad = 1'b0;

        #10;

        $display("CASO 15 - DED: SYNDROME 111");
        $display("  Recibida  : %b", hamming_recibido);
        $display("  Syndrome  : %b", syndrome);
        $display("  Paridad   : %b", error_paridad);
        $display("  Corregida : %b", palabra_corregida);
        $display("  SEC       : %b", sec);
        $display("  DED       : %b", ded);

        if (palabra_corregida == hamming_recibido &&
            sec == 1'b0 &&
            ded == 1'b1)
            $display("  RESULTADO: OK");
        else
            $display("  RESULTADO: ERROR");

        $display("");


        /*
         * ======================================================
         * CASO 16 - ERROR EN PARIDAD GLOBAL
         * ======================================================
         *
         * Paridad = 1
         * Syndrome = 000
         *
         * El error esta en el bit de paridad global,
         * por lo que los 7 bits Hamming permanecen iguales.
         */

        hamming_recibido = 7'b1010101;
        syndrome = 3'b000;
        error_paridad = 1'b1;

        #10;

        $display("CASO 16 - ERROR EN PARIDAD GLOBAL");
        $display("  Recibida  : %b", hamming_recibido);
        $display("  Syndrome  : %b", syndrome);
        $display("  Paridad   : %b", error_paridad);
        $display("  Corregida : %b", palabra_corregida);
        $display("  SEC       : %b", sec);
        $display("  DED       : %b", ded);

        if (palabra_corregida == 7'b1010101 &&
            sec == 1'b0 &&
            ded == 1'b0)
            $display("  RESULTADO: OK");
        else
            $display("  RESULTADO: ERROR");

        $display("");


        $display("============================================================");
        $display("              FIN DEL TESTBENCH");
        $display("============================================================");

        $finish;

    end

endmodule

build/error_correction.vcd
$date
	Tue Sep 22 04:02:42 2026
$end
$version
	Icarus Verilog
$end
$timescale
	1ps
$end
$scope module tb_error_correction $end
$var wire 1 ! sec $end
$var wire 7 " palabra_corregida [6:0] $end
$var wire 1 # ded $end
$var reg 1 $ error_paridad $end
$var reg 7 % hamming_recibido [6:0] $end
$var reg 3 & syndrome [2:0] $end
$scope module dut $end
$var wire 1 ' corregir_1 $end
$var wire 1 ( corregir_2 $end
$var wire 1 ) corregir_3 $end
$var wire 1 * corregir_4 $end
$var wire 1 + corregir_5 $end
$var wire 1 , corregir_6 $end
$var wire 1 - corregir_7 $end
$var wire 1 # ded $end
$var wire 1 $ error_paridad $end
$var wire 7 . hamming_recibido [6:0] $end
$var wire 1 ! sec $end
$var wire 3 / syndrome [2:0] $end
$var wire 1 0 syndrome_activo $end
$var wire 7 1 palabra_corregida [6:0] $end
$upscope $end
$upscope $end
$enddefinitions $end
$comment Show the parameter values. $end
$dumpall
$end
#0
$dumpvars
b1010101 1
00
b0 /
b1010101 .
0-
0,
0+
0*
0)
0(
0'
b0 &
b1010101 %
0$
0#
b1010101 "
0!
$end
#10000
1'
1!
10
b1010101 "
b1010101 1
1$
b1 &
b1 /
b1010100 %
b1010100 .
#20000
1!
1(
10
0'
b1010101 "
b1010101 1
b10 &
b10 /
b1010111 %
b1010111 .
#30000
0(
1)
b1010101 "
b1010101 1
b11 &
b11 /
b1010001 %
b1010001 .
#40000
1*
0)
b1010101 "
b1010101 1
b100 &
b100 /
b1011101 %
b1011101 .
#50000
0*
1+
b1010101 "
b1010101 1
b101 &
b101 /
b1000101 %
b1000101 .
#60000
0*
1,
0+
b1010101 "
b1010101 1
b110 &
b110 /
b1110101 %
b1110101 .
#70000
0,
1-
b1010101 "
b1010101 1
b111 &
b111 /
b10101 %
b10101 .
#80000
0-
1#
b1010100 "
b1010100 1
0!
0$
b1 &
b1 /
b1010100 %
b1010100 .
#90000
1#
10
b1010111 "
b1010111 1
b10 &
b10 /
b1010111 %
b1010111 .
#100000
b1010001 "
b1010001 1
b11 &
b11 /
b1010001 %
b1010001 .
#110000
b1011101 "
b1011101 1
b100 &
b100 /
b1011101 %
b1011101 .
#120000
b1000101 "
b1000101 1
b101 &
b101 /
b1000101 %
b1000101 .
#130000
b1110101 "
b1110101 1
b110 &
b110 /
b1110101 %
b1110101 .
#140000
b10101 "
b10101 1
b111 &
b111 /
b10101 %
b10101 .
#150000
00
0#
b1010101 "
b1010101 1
0!
1$
b0 &
b0 /
b1010101 %
b1010101 .
