design/Inyeccion_Error_Hamming.sv

module Inyeccion_Error_Hamming (

    input  wire [3:0] datos_i,

    input  wire I1_i,
    input  wire I2_i,
    input  wire I3_i,

    input  wire [2:0] err1_pos_i,
    input  wire [2:0] err2_pos_i,

    input  wire error_P_i,

    output wire D0_o,
    output wire D1_o,
    output wire D2_o,
    output wire D3_o,

    output wire I1_o,
    output wire I2_o,
    output wire I3_o,

    output wire P_o
);

    // =========================================================
    // PALABRA HAMMING DE ENTRADA
    //
    // bit 0 = D0
    // bit 1 = D1
    // bit 2 = D2
    // bit 3 = D3
    // bit 4 = I1
    // bit 5 = I2
    // bit 6 = I3
    // bit 7 = P
    //
    // P se calcula a partir de las paridades.
    // error_P_i NO forma parte de la palabra base.
    // =========================================================

    wire [7:0] palabra_base;

    assign palabra_base = {
        (I1_i ^ I2_i ^ I3_i),  // bit 7 = P
        I3_i,                  // bit 6
        I2_i,                  // bit 5
        I1_i,                  // bit 4
        datos_i[3],            // bit 3
        datos_i[2],            // bit 2
        datos_i[1],            // bit 1
        datos_i[0]             // bit 0
    };


    // =========================================================
    // MASCARA ERROR 1
    //
    // 000 = ningún error
    // 001 = D0
    // 010 = D1
    // 011 = D2
    // 100 = D3
    // 101 = I1
    // 110 = I2
    // 111 = I3
    // =========================================================

    reg [7:0] mask_error1;

    always @(*) begin

        case (err1_pos_i)

            3'b000: mask_error1 = 8'b00000000;

            3'b001: mask_error1 = 8'b00000001; // D0
            3'b010: mask_error1 = 8'b00000010; // D1
            3'b011: mask_error1 = 8'b00000100; // D2
            3'b100: mask_error1 = 8'b00001000; // D3

            3'b101: mask_error1 = 8'b00010000; // I1
            3'b110: mask_error1 = 8'b00100000; // I2
            3'b111: mask_error1 = 8'b01000000; // I3

            default: mask_error1 = 8'b00000000;

        endcase

    end


    // =========================================================
    // MASCARA ERROR 2
    // =========================================================

    reg [7:0] mask_error2;

    always @(*) begin

        case (err2_pos_i)

            3'b000: mask_error2 = 8'b00000000;

            3'b001: mask_error2 = 8'b00000001; // D0
            3'b010: mask_error2 = 8'b00000010; // D1
            3'b011: mask_error2 = 8'b00000100; // D2
            3'b100: mask_error2 = 8'b00001000; // D3

            3'b101: mask_error2 = 8'b00010000; // I1
            3'b110: mask_error2 = 8'b00100000; // I2
            3'b111: mask_error2 = 8'b01000000; // I3

            default: mask_error2 = 8'b00000000;

        endcase

    end


    // =========================================================
    // ERROR DE PARIDAD GLOBAL
    //
    // error_P_i = 1 -> invertir P
    // error_P_i = 0 -> no modificar P
    // =========================================================

    wire [7:0] mask_errorP;

    assign mask_errorP = error_P_i
                       ? 8'b10000000
                       : 8'b00000000;


    // =========================================================
    // PALABRA FINAL CON ERRORES
    // =========================================================

    wire [7:0] palabra_con_error;

    assign palabra_con_error =
            palabra_base
          ^ mask_error1
          ^ mask_error2
          ^ mask_errorP;


    // =========================================================
    // SALIDAS
    // =========================================================

    assign D0_o = palabra_con_error[0];
    assign D1_o = palabra_con_error[1];
    assign D2_o = palabra_con_error[2];
    assign D3_o = palabra_con_error[3];

    assign I1_o = palabra_con_error[4];
    assign I2_o = palabra_con_error[5];
    assign I3_o = palabra_con_error[6];

    assign P_o = palabra_con_error[7];

endmodule

sim/sim/tb_Inyeccion_Error_Hamming.sv
`timescale 1ns/1ps

module tb_Inyeccion_Error_Hamming;

    // =========================================================
    // ENTRADAS
    // =========================================================

    logic [3:0] datos_i;

    logic I1_i;
    logic I2_i;
    logic I3_i;

    logic [2:0] err1_pos_i;
    logic [2:0] err2_pos_i;

    logic error_P_i;


    // =========================================================
    // SALIDAS
    // =========================================================

    wire D0_o;
    wire D1_o;
    wire D2_o;
    wire D3_o;

    wire I1_o;
    wire I2_o;
    wire I3_o;

    wire P_o;


    // =========================================================
    // PALABRA HAMMING DE SALIDA
    //
    // [7] = P
    // [6] = I3
    // [5] = I2
    // [4] = I1
    // [3] = D3
    // [2] = D2
    // [1] = D1
    // [0] = D0
    // =========================================================

    wire [7:0] palabra_salida;

    assign palabra_salida = {
        P_o,
        I3_o,
        I2_o,
        I1_o,
        D3_o,
        D2_o,
        D1_o,
        D0_o
    };


    // =========================================================
    // INSTANCIA DEL MODULO
    // =========================================================

    Inyeccion_Error_Hamming uut (

        .datos_i(datos_i),

        .I1_i(I1_i),
        .I2_i(I2_i),
        .I3_i(I3_i),

        .err1_pos_i(err1_pos_i),
        .err2_pos_i(err2_pos_i),

        .error_P_i(error_P_i),

        .D0_o(D0_o),
        .D1_o(D1_o),
        .D2_o(D2_o),
        .D3_o(D3_o),

        .I1_o(I1_o),
        .I2_o(I2_o),
        .I3_o(I3_o),

        .P_o(P_o)
    );


    // =========================================================
    // CONTADORES DE PRUEBAS
    // =========================================================

    integer pruebas_totales;
    integer pruebas_correctas;


    // =========================================================
    // TAREA DE PRUEBA
    // =========================================================

    task automatic probar;

        input logic [3:0] dato;
        input logic [2:0] error1;
        input logic [2:0] error2;
        input logic errorP;

        logic i1_esperado;
        logic i2_esperado;
        logic i3_esperado;

        logic [7:0] palabra_base;
        logic [7:0] mascara1;
        logic [7:0] mascara2;
        logic [7:0] palabra_esperada;

        begin

            // -------------------------------------------------
            // DATOS DE ENTRADA
            // -------------------------------------------------

            datos_i = dato;

            err1_pos_i = error1;
            err2_pos_i = error2;

            error_P_i = errorP;


            // -------------------------------------------------
            // CALCULO DE PARIDADES
            // -------------------------------------------------

            i1_esperado = dato[0] ^ dato[1] ^ dato[3];

            i2_esperado = dato[0] ^ dato[2] ^ dato[3];

            i3_esperado = dato[1] ^ dato[2] ^ dato[3];


            I1_i = i1_esperado;
            I2_i = i2_esperado;
            I3_i = i3_esperado;


            // Esperar propagacion combinacional

            #10;


            // -------------------------------------------------
            // PALABRA BASE
            // -------------------------------------------------

            palabra_base = {
                i1_esperado ^ i2_esperado ^ i3_esperado,
                i3_esperado,
                i2_esperado,
                i1_esperado,
                dato[3],
                dato[2],
                dato[1],
                dato[0]
            };


            // -------------------------------------------------
            // MASCARA ERROR 1
            // -------------------------------------------------

            case (error1)

                3'b000: mascara1 = 8'b00000000;
                3'b001: mascara1 = 8'b00000001;
                3'b010: mascara1 = 8'b00000010;
                3'b011: mascara1 = 8'b00000100;
                3'b100: mascara1 = 8'b00001000;
                3'b101: mascara1 = 8'b00010000;
                3'b110: mascara1 = 8'b00100000;
                3'b111: mascara1 = 8'b01000000;

                default: mascara1 = 8'b00000000;

            endcase


            // -------------------------------------------------
            // MASCARA ERROR 2
            // -------------------------------------------------

            case (error2)

                3'b000: mascara2 = 8'b00000000;
                3'b001: mascara2 = 8'b00000001;
                3'b010: mascara2 = 8'b00000010;
                3'b011: mascara2 = 8'b00000100;
                3'b100: mascara2 = 8'b00001000;
                3'b101: mascara2 = 8'b00010000;
                3'b110: mascara2 = 8'b00100000;
                3'b111: mascara2 = 8'b01000000;

                default: mascara2 = 8'b00000000;

            endcase


            // -------------------------------------------------
            // PALABRA ESPERADA
            // -------------------------------------------------

            palabra_esperada =
                palabra_base ^
                mascara1 ^
                mascara2;

            palabra_esperada[7] =
                palabra_esperada[7] ^ errorP;


            // -------------------------------------------------
            // MOSTRAR PRUEBA
            // -------------------------------------------------

            pruebas_totales = pruebas_totales + 1;

            $display("");
            $display("------------------------------------------------------------");

            $display("PRUEBA #%0d", pruebas_totales);

            $display("Datos       : %04b", dato);

            $display("I1 I2 I3    : %b %b %b",
                     i1_esperado,
                     i2_esperado,
                     i3_esperado);

            $display("Error 1     : %03b", error1);

            $display("Error 2     : %03b", error2);

            $display("Error P     : %b", errorP);

            $display("Base        : %08b  HEX: %02h",
                     palabra_base,
                     palabra_base);

            $display("Esperada    : %08b  HEX: %02h",
                     palabra_esperada,
                     palabra_esperada);

            $display("Salida      : %08b  HEX: %02h",
                     palabra_salida,
                     palabra_salida);


            // -------------------------------------------------
            // VERIFICACION
            // -------------------------------------------------

            if (palabra_salida === palabra_esperada) begin

                $display("RESULTADO   : OK");

                pruebas_correctas =
                    pruebas_correctas + 1;

            end
            else begin

                $display("RESULTADO   : ERROR");

                $display("Diferencia  : %08b",
                         palabra_salida ^ palabra_esperada);

            end

        end

    endtask


    // =========================================================
    // INICIO DE SIMULACION
    // =========================================================

    initial begin

        pruebas_totales = 0;
        pruebas_correctas = 0;


        // =====================================================
        // VCD
        // =====================================================

        $dumpfile("Inyeccion_Error_Hamming.vcd");
        $dumpvars(0, tb_Inyeccion_Error_Hamming);


        // =====================================================
        // ENCABEZADO
        // =====================================================

        $display("");
        $display("============================================================");
        $display("       TESTBENCH INYECCION DE ERROR HAMMING");
        $display("============================================================");

        $display("");
        $display("Formato:");
        $display("[P I3 I2 I1 D3 D2 D1 D0]");

        $display("");
        $display("Codigos de error:");
        $display("000 = Sin error");
        $display("001 = D0");
        $display("010 = D1");
        $display("011 = D2");
        $display("100 = D3");
        $display("101 = I1");
        $display("110 = I2");
        $display("111 = I3");


        // =====================================================
        // 1. SIN ERROR
        // =====================================================

        probar(
            4'b0000,
            3'b000,
            3'b000,
            1'b0
        );


        // =====================================================
        // 2. DATO 1010 SIN ERROR
        // =====================================================

        probar(
            4'b1010,
            3'b000,
            3'b000,
            1'b0
        );


        // =====================================================
        // 3. ERROR D0
        // =====================================================

        probar(
            4'b1010,
            3'b001,
            3'b000,
            1'b0
        );


        // =====================================================
        // 4. ERROR D1
        // =====================================================

        probar(
            4'b1010,
            3'b010,
            3'b000,
            1'b0
        );


        // =====================================================
        // 5. ERROR D2
        // =====================================================

        probar(
            4'b1010,
            3'b011,
            3'b000,
            1'b0
        );


        // =====================================================
        // 6. ERROR D3
        // =====================================================

        probar(
            4'b1010,
            3'b100,
            3'b000,
            1'b0
        );


        // =====================================================
        // 7. ERROR I1
        // =====================================================

        probar(
            4'b1010,
            3'b101,
            3'b000,
            1'b0
        );


        // =====================================================
        // 8. ERROR I2
        // =====================================================

        probar(
            4'b1010,
            3'b110,
            3'b000,
            1'b0
        );


        // =====================================================
        // 9. ERROR I3
        // =====================================================

        probar(
            4'b1010,
            3'b111,
            3'b000,
            1'b0
        );


        // =====================================================
        // 10. ERROR EN P
        // =====================================================

        probar(
            4'b1010,
            3'b000,
            3'b000,
            1'b1
        );


        // =====================================================
        // 11. DOS ERRORES: D0 + D1
        // =====================================================

        probar(
            4'b1010,
            3'b001,
            3'b010,
            1'b0
        );


        // =====================================================
        // 12. DOS ERRORES: I1 + I2
        // =====================================================

        probar(
            4'b1010,
            3'b101,
            3'b110,
            1'b0
        );


        // =====================================================
        // 13. DOS ERRORES + P
        // =====================================================

        probar(
            4'b1010,
            3'b011,
            3'b111,
            1'b1
        );


        // =====================================================
        // 14. OTRA PALABRA
        // =====================================================

        probar(
            4'b1111,
            3'b001,
            3'b100,
            1'b0
        );

        probar(
            4'b0101,
            3'b101,
            3'b000,
            1'b1
        );

        probar(
            4'b1100,
            3'b000,
            3'b111,
            1'b1
        );

        $display("");
        $display("============================================================");
        $display("                    RESUMEN FINAL");

        $display("Pruebas realizadas : %0d",
                 pruebas_totales);

        $display("Pruebas correctas  : %0d",
                 pruebas_correctas);

        $display("Pruebas con error  : %0d",
                 pruebas_totales - pruebas_correctas);

        if (pruebas_totales == pruebas_correctas) begin

            $display("");
            $display("******** TODAS LAS PRUEBAS PASARON ********");

        end
        else begin

            $display("");
            $display("******** HAY PRUEBAS CON ERROR ********");

        end

        $display("============================================================");
        $display("");


        $finish;

    end

endmodule

build/Inyeccion_Error_Hamming.vcd
$date
	Tue Sep 22 04:02:07 2026
$end
$version
	Icarus Verilog
$end
$timescale
	1ps
$end
$scope module tb_Inyeccion_Error_Hamming $end
$var wire 8 ! palabra_salida [7:0] $end
$var wire 1 " P_o $end
$var wire 1 # I3_o $end
$var wire 1 $ I2_o $end
$var wire 1 % I1_o $end
$var wire 1 & D3_o $end
$var wire 1 ' D2_o $end
$var wire 1 ( D1_o $end
$var wire 1 ) D0_o $end
$var reg 1 * I1_i $end
$var reg 1 + I2_i $end
$var reg 1 , I3_i $end
$var reg 4 - datos_i [3:0] $end
$var reg 3 . err1_pos_i [2:0] $end
$var reg 3 / err2_pos_i [2:0] $end
$var reg 1 0 error_P_i $end
$var integer 32 1 pruebas_correctas [31:0] $end
$var integer 32 2 pruebas_totales [31:0] $end
$scope module uut $end
$var wire 1 * I1_i $end
$var wire 1 + I2_i $end
$var wire 1 , I3_i $end
$var wire 4 3 datos_i [3:0] $end
$var wire 3 4 err1_pos_i [2:0] $end
$var wire 3 5 err2_pos_i [2:0] $end
$var wire 1 0 error_P_i $end
$var wire 8 6 palabra_con_error [7:0] $end
$var wire 8 7 palabra_base [7:0] $end
$var wire 8 8 mask_errorP [7:0] $end
$var wire 1 " P_o $end
$var wire 1 # I3_o $end
$var wire 1 $ I2_o $end
$var wire 1 % I1_o $end
$var wire 1 & D3_o $end
$var wire 1 ' D2_o $end
$var wire 1 ( D1_o $end
$var wire 1 ) D0_o $end
$var reg 8 9 mask_error1 [7:0] $end
$var reg 8 : mask_error2 [7:0] $end
$upscope $end
$scope task probar $end
$upscope $end
$upscope $end
$enddefinitions $end
$comment Show the parameter values. $end
$dumpall
$end
#0
$dumpvars
b0 :
b0 9
b0 8
b0 7
b0 6
b0 5
b0 4
b0 3
b0 2
b0 1
00
b0 /
b0 .
b0 -
0,
0+
0*
0)
0(
0'
0&
0%
0$
0#
0"
b0 !
$end
#10000
1"
1(
1&
b10101010 !
1$
b10101010 6
b10101010 7
1+
b1010 -
b1010 3
b1 1
b1 2
#20000
b10101011 !
1)
b10101011 6
b1 9
b1 .
b1 4
b10 1
b10 2
#30000
0)
b10101000 !
0(
b10101000 6
b10 9
b10 .
b10 4
b11 1
b11 2
#40000
1(
b10101110 !
1'
b10101110 6
b100 9
b11 .
b11 4
b100 1
b100 2
#50000
0'
b10100010 !
0&
b10100010 6
b1000 9
b100 .
b100 4
b101 1
b101 2
#60000
1&
b10111010 !
1%
b10111010 6
b10000 9
b101 .
b101 4
b110 1
b110 2
#70000
0%
b10001010 !
0$
b10001010 6
b100000 9
b110 .
b110 4
b111 1
b111 2
#80000
1$
b11101010 !
1#
b11101010 6
b1000000 9
b111 .
b111 4
b1000 1
b1000 2
#90000
0#
b101010 !
0"
b101010 6
b10000000 8
b0 9
10
b0 .
b0 4
b1001 1
b1001 2
#100000
1)
0(
b10101001 !
1"
b10101001 6
b0 8
b10 :
b1 9
00
b10 /
b10 5
b1 .
b1 4
b1010 1
b1010 2
#110000
0)
1(
1%
b10011010 !
0$
b10011010 6
b100000 :
b10000 9
b110 /
b110 5
b101 .
b101 4
b1011 1
b1011 2
#120000
1'
0%
1$
1#
b1101110 !
0"
b1101110 6
b10000000 8
b1000000 :
b100 9
10
b111 /
b111 5
b11 .
b11 4
b1100 1
b1100 2
#130000
0&
1%
b11110110 !
1"
b11110110 6
b0 8
b1000 :
b1 9
1,
b11111111 7
1*
00
b100 /
b100 5
b1 .
b1 4
b1111 -
b1111 3
b1101 1
b1101 2
#140000
1)
0(
0%
0$
b11000101 !
1"
b11000101 6
b10000000 8
b0 :
b10000 9
b1010101 7
0+
10
b0 /
b0 5
b101 .
b101 4
b101 -
b101 3
b1110 1
b1110 2
#150000
0"
0)
1&
b1011100 !
1%
b1011100 6
b1000000 :
b0 9
b10011100 7
0,
b111 /
b111 5
b0 .
b0 4
b1100 -
b1100 3
b1111 1
b1111 2
#160000
b10000 1
b10000 2
