design/parity_decoder.sv
module parity_decoder (
    input wire [7:0] palabra_recibida,

    output wire paridad_ok,
    output wire error_paridad
);

    wire xor_01;
    wire xor_23;
    wire xor_45;
    wire xor_67;

    wire xor_0123;
    wire xor_4567;

    wire paridad_total;

    // ==========================================
    // PRIMERA ETAPA
    // ==========================================

    assign xor_01 = palabra_recibida[0] ^ palabra_recibida[1];
    assign xor_23 = palabra_recibida[2] ^ palabra_recibida[3];
    assign xor_45 = palabra_recibida[4] ^ palabra_recibida[5];
    assign xor_67 = palabra_recibida[6] ^ palabra_recibida[7];

    // ==========================================
    // SEGUNDA ETAPA
    // ==========================================

    assign xor_0123 = xor_01 ^ xor_23;
    assign xor_4567 = xor_45 ^ xor_67;

    // ==========================================
    // PARIDAD GLOBAL
    // ==========================================

    assign paridad_total = xor_0123 ^ xor_4567;

    // ==========================================
    // PARIDAD PAR
    //
    // 0 = cantidad par de unos
    // 1 = cantidad impar de unos
    // ==========================================

    assign paridad_ok    = ~paridad_total;
    assign error_paridad = paridad_total;

endmodule

EL_3307_Proyecto1_1/sim/tb_parity_decoder.sv
`timescale 1ns/1ps

module tb_parity_decoder;

    reg [7:0] palabra_recibida;

    wire paridad_ok;
    wire error_paridad;

    integer i;
    integer unos;
    integer errores;

    parity_decoder dut (
        .palabra_recibida(palabra_recibida),
        .paridad_ok(paridad_ok),
        .error_paridad(error_paridad)
    );

    initial begin

        $dumpfile("parity_decoder.vcd");
        $dumpvars(0, tb_parity_decoder);

        $display("================================================================");
        $display("             TESTBENCH DECODIFICADOR DE PARIDAD");
        $display("                 PRUEBA DE 256 COMBINACIONES");
        $display("================================================================");
        $display("  #     ENTRADA     # UNOS     PARIDAD     SALIDA");
        $display("----------------------------------------------------------------");

        errores = 0;

        for (i = 0; i < 256; i = i + 1) begin

            palabra_recibida = i;

            #10;

            unos = palabra_recibida[0] +
                   palabra_recibida[1] +
                   palabra_recibida[2] +
                   palabra_recibida[3] +
                   palabra_recibida[4] +
                   palabra_recibida[5] +
                   palabra_recibida[6] +
                   palabra_recibida[7];

            if ((unos % 2) == 0) begin

                if (paridad_ok == 1'b1 && error_paridad == 1'b0) begin
                    $display("%3d     %08b         %1d        PAR          OK",
                             i, palabra_recibida, unos);
                end
                else begin
                    $display("%3d     %08b         %1d        PAR          ERROR",
                             i, palabra_recibida, unos);
                    errores = errores + 1;
                end

            end
            else begin

                if (paridad_ok == 1'b0 && error_paridad == 1'b1) begin
                    $display("%3d     %08b         %1d       IMPAR         OK",
                             i, palabra_recibida, unos);
                end
                else begin
                    $display("%3d     %08b         %1d       IMPAR         ERROR",
                             i, palabra_recibida, unos);
                    errores = errores + 1;
                end

            end

        end

        $display("----------------------------------------------------------------");
        $display("TOTAL DE COMBINACIONES PROBADAS: 256");
        $display("TOTAL DE ERRORES: %0d", errores);

        if (errores == 0)
            $display("RESULTADO FINAL: TODAS LAS COMBINACIONES FUNCIONAN");
        else
            $display("RESULTADO FINAL: HAY ERRORES EN EL CIRCUITO");

        $display("================================================================");

        $finish;

    end

endmodule

build/parity_decoder.vcd
$date
	Tue Sep 22 04:02:22 2026
$end
$version
	Icarus Verilog
$end
$timescale
	1ps
$end
$scope module tb_parity_decoder $end
$var wire 1 ! paridad_ok $end
$var wire 1 " error_paridad $end
$var reg 8 # palabra_recibida [7:0] $end
$var integer 32 $ errores [31:0] $end
$var integer 32 % i [31:0] $end
$var integer 32 & unos [31:0] $end
$scope module dut $end
$var wire 1 " error_paridad $end
$var wire 8 ' palabra_recibida [7:0] $end
$var wire 1 ! paridad_ok $end
$var wire 1 ( paridad_total $end
$var wire 1 ) xor_01 $end
$var wire 1 * xor_0123 $end
$var wire 1 + xor_23 $end
$var wire 1 , xor_45 $end
$var wire 1 - xor_4567 $end
$var wire 1 . xor_67 $end
$upscope $end
$upscope $end
$enddefinitions $end
$comment Show the parameter values. $end
$dumpall
$end
#0
$dumpvars
0.
0-
0,
0+
0*
0)
0(
b0 '
bx &
b0 %
b0 $
b0 #
0"
1!
$end
#10000
0!
1"
1(
1*
1)
b1 #
b1 '
b1 %
b0 &
#20000
b10 #
b10 '
b10 %
b1 &
#30000
1!
0"
0(
0*
0)
b11 #
b11 '
b11 %
#40000
0!
1"
1(
1*
1+
b100 #
b100 '
b100 %
b10 &
#50000
1!
0"
0(
0*
1)
b101 #
b101 '
b101 %
b1 &
#60000
b110 #
b110 '
b110 %
b10 &
#70000
0!
1"
1(
1*
0)
b111 #
b111 '
b111 %
#80000
b1000 #
b1000 '
b1000 %
b11 &
#90000
1!
0"
0(
0*
1)
b1001 #
b1001 '
b1001 %
b1 &
#100000
b1010 #
b1010 '
b1010 %
b10 &
#110000
0!
1"
1(
1*
0)
b1011 #
b1011 '
b1011 %
#120000
1!
0"
0(
0*
0+
b1100 #
b1100 '
b1100 %
b11 &
#130000
0!
1"
1(
1*
1)
b1101 #
b1101 '
b1101 %
b10 &
#140000
b1110 #
b1110 '
b1110 %
b11 &
#150000
1!
0"
0(
0*
0)
b1111 #
b1111 '
b1111 %
#160000
0!
1"
1(
1-
1,
b10000 #
b10000 '
b10000 %
b100 &
#170000
1!
0"
0(
1*
1)
b10001 #
b10001 '
b10001 %
b1 &
#180000
b10010 #
b10010 '
b10010 %
b10 &
#190000
0!
1"
1(
0*
0)
b10011 #
b10011 '
b10011 %
#200000
1!
0"
0(
1*
1+
b10100 #
b10100 '
b10100 %
b11 &
#210000
0!
1"
1(
0*
1)
b10101 #
b10101 '
b10101 %
b10 &
#220000
b10110 #
b10110 '
b10110 %
b11 &
#230000
1!
0"
0(
1*
0)
b10111 #
b10111 '
b10111 %
#240000
b11000 #
b11000 '
b11000 %
b100 &
#250000
0!
1"
1(
0*
1)
b11001 #
b11001 '
b11001 %
b10 &
#260000
b11010 #
b11010 '
b11010 %
b11 &
#270000
1!
0"
0(
1*
0)
b11011 #
b11011 '
b11011 %
#280000
0!
1"
1(
0*
0+
b11100 #
b11100 '
b11100 %
b100 &
#290000
1!
0"
0(
1*
1)
b11101 #
b11101 '
b11101 %
b11 &
#300000
b11110 #
b11110 '
b11110 %
b100 &
#310000
0!
1"
1(
0*
0)
b11111 #
b11111 '
b11111 %
#320000
b100000 #
b100000 '
b100000 %
b101 &
#330000
1!
0"
0(
1*
1)
b100001 #
b100001 '
b100001 %
b1 &
#340000
b100010 #
b100010 '
b100010 %
b10 &
#350000
0!
1"
1(
0*
0)
b100011 #
b100011 '
b100011 %
#360000
1!
0"
0(
1*
1+
b100100 #
b100100 '
b100100 %
b11 &
#370000
0!
1"
1(
0*
1)
b100101 #
b100101 '
b100101 %
b10 &
#380000
b100110 #
b100110 '
b100110 %
b11 &
#390000
1!
0"
0(
1*
0)
b100111 #
b100111 '
b100111 %
#400000
b101000 #
b101000 '
b101000 %
b100 &
#410000
0!
1"
1(
0*
1)
b101001 #
b101001 '
b101001 %
b10 &
#420000
b101010 #
b101010 '
b101010 %
b11 &
#430000
1!
0"
0(
1*
0)
b101011 #
b101011 '
b101011 %
#440000
0!
1"
1(
0*
0+
b101100 #
b101100 '
b101100 %
b100 &
#450000
1!
0"
0(
1*
1)
b101101 #
b101101 '
b101101 %
b11 &
#460000
b101110 #
b101110 '
b101110 %
b100 &
#470000
0!
1"
1(
0*
0)
b101111 #
b101111 '
b101111 %
#480000
1!
0"
0(
0-
0,
b110000 #
b110000 '
b110000 %
b101 &
#490000
0!
1"
1(
1*
1)
b110001 #
b110001 '
b110001 %
b10 &
#500000
b110010 #
b110010 '
b110010 %
b11 &
#510000
1!
0"
0(
0*
0)
b110011 #
b110011 '
b110011 %
#520000
0!
1"
1(
1*
1+
b110100 #
b110100 '
b110100 %
b100 &
#530000
1!
0"
0(
0*
1)
b110101 #
b110101 '
b110101 %
b11 &
#540000
b110110 #
b110110 '
b110110 %
b100 &
#550000
0!
1"
1(
1*
0)
b110111 #
b110111 '
b110111 %
#560000
b111000 #
b111000 '
b111000 %
b101 &
#570000
1!
0"
0(
0*
1)
b111001 #
b111001 '
b111001 %
b11 &
#580000
b111010 #
b111010 '
b111010 %
b100 &
#590000
0!
1"
1(
1*
0)
b111011 #
b111011 '
b111011 %
#600000
1!
0"
0(
0*
0+
b111100 #
b111100 '
b111100 %
b101 &
#610000
0!
1"
1(
1*
1)
b111101 #
b111101 '
b111101 %
b100 &
#620000
b111110 #
b111110 '
b111110 %
b101 &
#630000
1!
0"
0(
0*
0)
b111111 #
b111111 '
b111111 %
#640000
0!
1"
1(
1-
1.
b1000000 #
b1000000 '
b1000000 %
b110 &
#650000
1!
0"
0(
1*
1)
b1000001 #
b1000001 '
b1000001 %
b1 &
#660000
b1000010 #
b1000010 '
b1000010 %
b10 &
#670000
0!
1"
1(
0*
0)
b1000011 #
b1000011 '
b1000011 %
#680000
1!
0"
0(
1*
1+
b1000100 #
b1000100 '
b1000100 %
b11 &
#690000
0!
1"
1(
0*
1)
b1000101 #
b1000101 '
b1000101 %
b10 &
#700000
b1000110 #
b1000110 '
b1000110 %
b11 &
#710000
1!
0"
0(
1*
0)
b1000111 #
b1000111 '
b1000111 %
#720000
b1001000 #
b1001000 '
b1001000 %
b100 &
#730000
0!
1"
1(
0*
1)
b1001001 #
b1001001 '
b1001001 %
b10 &
#740000
b1001010 #
b1001010 '
b1001010 %
b11 &
#750000
1!
0"
0(
1*
0)
b1001011 #
b1001011 '
b1001011 %
#760000
0!
1"
1(
0*
0+
b1001100 #
b1001100 '
b1001100 %
b100 &
#770000
1!
0"
0(
1*
1)
b1001101 #
b1001101 '
b1001101 %
b11 &
#780000
b1001110 #
b1001110 '
b1001110 %
b100 &
#790000
0!
1"
1(
0*
0)
b1001111 #
b1001111 '
b1001111 %
#800000
1!
0"
0(
0-
1,
b1010000 #
b1010000 '
b1010000 %
b101 &
#810000
0!
1"
1(
1*
1)
b1010001 #
b1010001 '
b1010001 %
b10 &
#820000
b1010010 #
b1010010 '
b1010010 %
b11 &
#830000
1!
0"
0(
0*
0)
b1010011 #
b1010011 '
b1010011 %
#840000
0!
1"
1(
1*
1+
b1010100 #
b1010100 '
b1010100 %
b100 &
#850000
1!
0"
0(
0*
1)
b1010101 #
b1010101 '
b1010101 %
b11 &
#860000
b1010110 #
b1010110 '
b1010110 %
b100 &
#870000
0!
1"
1(
1*
0)
b1010111 #
b1010111 '
b1010111 %
#880000
b1011000 #
b1011000 '
b1011000 %
b101 &
#890000
1!
0"
0(
0*
1)
b1011001 #
b1011001 '
b1011001 %
b11 &
#900000
b1011010 #
b1011010 '
b1011010 %
b100 &
#910000
0!
1"
1(
1*
0)
b1011011 #
b1011011 '
b1011011 %
#920000
1!
0"
0(
0*
0+
b1011100 #
b1011100 '
b1011100 %
b101 &
#930000
0!
1"
1(
1*
1)
b1011101 #
b1011101 '
b1011101 %
b100 &
#940000
b1011110 #
b1011110 '
b1011110 %
b101 &
#950000
1!
0"
0(
0*
0)
b1011111 #
b1011111 '
b1011111 %
#960000
b1100000 #
b1100000 '
b1100000 %
b110 &
#970000
0!
1"
1(
1*
1)
b1100001 #
b1100001 '
b1100001 %
b10 &
#980000
b1100010 #
b1100010 '
b1100010 %
b11 &
#990000
1!
0"
0(
0*
0)
b1100011 #
b1100011 '
b1100011 %
#1000000
0!
1"
1(
1*
1+
b1100100 #
b1100100 '
b1100100 %
b100 &
#1010000
1!
0"
0(
0*
1)
b1100101 #
b1100101 '
b1100101 %
b11 &
#1020000
b1100110 #
b1100110 '
b1100110 %
b100 &
#1030000
0!
1"
1(
1*
0)
b1100111 #
b1100111 '
b1100111 %
#1040000
b1101000 #
b1101000 '
b1101000 %
b101 &
#1050000
1!
0"
0(
0*
1)
b1101001 #
b1101001 '
b1101001 %
b11 &
#1060000
b1101010 #
b1101010 '
b1101010 %
b100 &
#1070000
0!
1"
1(
1*
0)
b1101011 #
b1101011 '
b1101011 %
#1080000
1!
0"
0(
0*
0+
b1101100 #
b1101100 '
b1101100 %
b101 &
#1090000
0!
1"
1(
1*
1)
b1101101 #
b1101101 '
b1101101 %
b100 &
#1100000
b1101110 #
b1101110 '
b1101110 %
b101 &
#1110000
1!
0"
0(
0*
0)
b1101111 #
b1101111 '
b1101111 %
#1120000
0!
1"
1(
1-
0,
b1110000 #
b1110000 '
b1110000 %
b110 &
#1130000
1!
0"
0(
1*
1)
b1110001 #
b1110001 '
b1110001 %
b11 &
#1140000
b1110010 #
b1110010 '
b1110010 %
b100 &
#1150000
0!
1"
1(
0*
0)
b1110011 #
b1110011 '
b1110011 %
#1160000
1!
0"
0(
1*
1+
b1110100 #
b1110100 '
b1110100 %
b101 &
#1170000
0!
1"
1(
0*
1)
b1110101 #
b1110101 '
b1110101 %
b100 &
#1180000
b1110110 #
b1110110 '
b1110110 %
b101 &
#1190000
1!
0"
0(
1*
0)
b1110111 #
b1110111 '
b1110111 %
#1200000
b1111000 #
b1111000 '
b1111000 %
b110 &
#1210000
0!
1"
1(
0*
1)
b1111001 #
b1111001 '
b1111001 %
b100 &
#1220000
b1111010 #
b1111010 '
b1111010 %
b101 &
#1230000
1!
0"
0(
1*
0)
b1111011 #
b1111011 '
b1111011 %
#1240000
0!
1"
1(
0*
0+
b1111100 #
b1111100 '
b1111100 %
b110 &
#1250000
1!
0"
0(
1*
1)
b1111101 #
b1111101 '
b1111101 %
b101 &
#1260000
b1111110 #
b1111110 '
b1111110 %
b110 &
#1270000
0!
1"
1(
0*
0)
b1111111 #
b1111111 '
b1111111 %
#1280000
b10000000 #
b10000000 '
b10000000 %
b111 &
#1290000
1!
0"
0(
1*
1)
b10000001 #
b10000001 '
b10000001 %
b1 &
#1300000
b10000010 #
b10000010 '
b10000010 %
b10 &
#1310000
0!
1"
1(
0*
0)
b10000011 #
b10000011 '
b10000011 %
#1320000
1!
0"
0(
1*
1+
b10000100 #
b10000100 '
b10000100 %
b11 &
#1330000
0!
1"
1(
0*
1)
b10000101 #
b10000101 '
b10000101 %
b10 &
#1340000
b10000110 #
b10000110 '
b10000110 %
b11 &
#1350000
1!
0"
0(
1*
0)
b10000111 #
b10000111 '
b10000111 %
#1360000
b10001000 #
b10001000 '
b10001000 %
b100 &
#1370000
0!
1"
1(
0*
1)
b10001001 #
b10001001 '
b10001001 %
b10 &
#1380000
b10001010 #
b10001010 '
b10001010 %
b11 &
#1390000
1!
0"
0(
1*
0)
b10001011 #
b10001011 '
b10001011 %
#1400000
0!
1"
1(
0*
0+
b10001100 #
b10001100 '
b10001100 %
b100 &
#1410000
1!
0"
0(
1*
1)
b10001101 #
b10001101 '
b10001101 %
b11 &
#1420000
b10001110 #
b10001110 '
b10001110 %
b100 &
#1430000
0!
1"
1(
0*
0)
b10001111 #
b10001111 '
b10001111 %
#1440000
1!
0"
0(
0-
1,
b10010000 #
b10010000 '
b10010000 %
b101 &
#1450000
0!
1"
1(
1*
1)
b10010001 #
b10010001 '
b10010001 %
b10 &
#1460000
b10010010 #
b10010010 '
b10010010 %
b11 &
#1470000
1!
0"
0(
0*
0)
b10010011 #
b10010011 '
b10010011 %
#1480000
0!
1"
1(
1*
1+
b10010100 #
b10010100 '
b10010100 %
b100 &
#1490000
1!
0"
0(
0*
1)
b10010101 #
b10010101 '
b10010101 %
b11 &
#1500000
b10010110 #
b10010110 '
b10010110 %
b100 &
#1510000
0!
1"
1(
1*
0)
b10010111 #
b10010111 '
b10010111 %
#1520000
b10011000 #
b10011000 '
b10011000 %
b101 &
#1530000
1!
0"
0(
0*
1)
b10011001 #
b10011001 '
b10011001 %
b11 &
#1540000
b10011010 #
b10011010 '
b10011010 %
b100 &
#1550000
0!
1"
1(
1*
0)
b10011011 #
b10011011 '
b10011011 %
#1560000
1!
0"
0(
0*
0+
b10011100 #
b10011100 '
b10011100 %
b101 &
#1570000
0!
1"
1(
1*
1)
b10011101 #
b10011101 '
b10011101 %
b100 &
#1580000
b10011110 #
b10011110 '
b10011110 %
b101 &
#1590000
1!
0"
0(
0*
0)
b10011111 #
b10011111 '
b10011111 %
#1600000
b10100000 #
b10100000 '
b10100000 %
b110 &
#1610000
0!
1"
1(
1*
1)
b10100001 #
b10100001 '
b10100001 %
b10 &
#1620000
b10100010 #
b10100010 '
b10100010 %
b11 &
#1630000
1!
0"
0(
0*
0)
b10100011 #
b10100011 '
b10100011 %
#1640000
0!
1"
1(
1*
1+
b10100100 #
b10100100 '
b10100100 %
b100 &
#1650000
1!
0"
0(
0*
1)
b10100101 #
b10100101 '
b10100101 %
b11 &
#1660000
b10100110 #
b10100110 '
b10100110 %
b100 &
#1670000
0!
1"
1(
1*
0)
b10100111 #
b10100111 '
b10100111 %
#1680000
b10101000 #
b10101000 '
b10101000 %
b101 &
#1690000
1!
0"
0(
0*
1)
b10101001 #
b10101001 '
b10101001 %
b11 &
#1700000
b10101010 #
b10101010 '
b10101010 %
b100 &
#1710000
0!
1"
1(
1*
0)
b10101011 #
b10101011 '
b10101011 %
#1720000
1!
0"
0(
0*
0+
b10101100 #
b10101100 '
b10101100 %
b101 &
#1730000
0!
1"
1(
1*
1)
b10101101 #
b10101101 '
b10101101 %
b100 &
#1740000
b10101110 #
b10101110 '
b10101110 %
b101 &
#1750000
1!
0"
0(
0*
0)
b10101111 #
b10101111 '
b10101111 %
#1760000
0!
1"
1(
1-
0,
b10110000 #
b10110000 '
b10110000 %
b110 &
#1770000
1!
0"
0(
1*
1)
b10110001 #
b10110001 '
b10110001 %
b11 &
#1780000
b10110010 #
b10110010 '
b10110010 %
b100 &
#1790000
0!
1"
1(
0*
0)
b10110011 #
b10110011 '
b10110011 %
#1800000
1!
0"
0(
1*
1+
b10110100 #
b10110100 '
b10110100 %
b101 &
#1810000
0!
1"
1(
0*
1)
b10110101 #
b10110101 '
b10110101 %
b100 &
#1820000
b10110110 #
b10110110 '
b10110110 %
b101 &
#1830000
1!
0"
0(
1*
0)
b10110111 #
b10110111 '
b10110111 %
#1840000
b10111000 #
b10111000 '
b10111000 %
b110 &
#1850000
0!
1"
1(
0*
1)
b10111001 #
b10111001 '
b10111001 %
b100 &
#1860000
b10111010 #
b10111010 '
b10111010 %
b101 &
#1870000
1!
0"
0(
1*
0)
b10111011 #
b10111011 '
b10111011 %
#1880000
0!
1"
1(
0*
0+
b10111100 #
b10111100 '
b10111100 %
b110 &
#1890000
1!
0"
0(
1*
1)
b10111101 #
b10111101 '
b10111101 %
b101 &
#1900000
b10111110 #
b10111110 '
b10111110 %
b110 &
#1910000
0!
1"
1(
0*
0)
b10111111 #
b10111111 '
b10111111 %
#1920000
1!
0"
0(
0-
0.
b11000000 #
b11000000 '
b11000000 %
b111 &
#1930000
0!
1"
1(
1*
1)
b11000001 #
b11000001 '
b11000001 %
b10 &
#1940000
b11000010 #
b11000010 '
b11000010 %
b11 &
#1950000
1!
0"
0(
0*
0)
b11000011 #
b11000011 '
b11000011 %
#1960000
0!
1"
1(
1*
1+
b11000100 #
b11000100 '
b11000100 %
b100 &
#1970000
1!
0"
0(
0*
1)
b11000101 #
b11000101 '
b11000101 %
b11 &
#1980000
b11000110 #
b11000110 '
b11000110 %
b100 &
#1990000
0!
1"
1(
1*
0)
b11000111 #
b11000111 '
b11000111 %
#2000000
b11001000 #
b11001000 '
b11001000 %
b101 &
#2010000
1!
0"
0(
0*
1)
b11001001 #
b11001001 '
b11001001 %
b11 &
#2020000
b11001010 #
b11001010 '
b11001010 %
b100 &
#2030000
0!
1"
1(
1*
0)
b11001011 #
b11001011 '
b11001011 %
#2040000
1!
0"
0(
0*
0+
b11001100 #
b11001100 '
b11001100 %
b101 &
#2050000
0!
1"
1(
1*
1)
b11001101 #
b11001101 '
b11001101 %
b100 &
#2060000
b11001110 #
b11001110 '
b11001110 %
b101 &
#2070000
1!
0"
0(
0*
0)
b11001111 #
b11001111 '
b11001111 %
#2080000
0!
1"
1(
1-
1,
b11010000 #
b11010000 '
b11010000 %
b110 &
#2090000
1!
0"
0(
1*
1)
b11010001 #
b11010001 '
b11010001 %
b11 &
#2100000
b11010010 #
b11010010 '
b11010010 %
b100 &
#2110000
0!
1"
1(
0*
0)
b11010011 #
b11010011 '
b11010011 %
#2120000
1!
0"
0(
1*
1+
b11010100 #
b11010100 '
b11010100 %
b101 &
#2130000
0!
1"
1(
0*
1)
b11010101 #
b11010101 '
b11010101 %
b100 &
#2140000
b11010110 #
b11010110 '
b11010110 %
b101 &
#2150000
1!
0"
0(
1*
0)
b11010111 #
b11010111 '
b11010111 %
#2160000
b11011000 #
b11011000 '
b11011000 %
b110 &
#2170000
0!
1"
1(
0*
1)
b11011001 #
b11011001 '
b11011001 %
b100 &
#2180000
b11011010 #
b11011010 '
b11011010 %
b101 &
#2190000
1!
0"
0(
1*
0)
b11011011 #
b11011011 '
b11011011 %
#2200000
0!
1"
1(
0*
0+
b11011100 #
b11011100 '
b11011100 %
b110 &
#2210000
1!
0"
0(
1*
1)
b11011101 #
b11011101 '
b11011101 %
b101 &
#2220000
b11011110 #
b11011110 '
b11011110 %
b110 &
#2230000
0!
1"
1(
0*
0)
b11011111 #
b11011111 '
b11011111 %
#2240000
b11100000 #
b11100000 '
b11100000 %
b111 &
#2250000
1!
0"
0(
1*
1)
b11100001 #
b11100001 '
b11100001 %
b11 &
#2260000
b11100010 #
b11100010 '
b11100010 %
b100 &
#2270000
0!
1"
1(
0*
0)
b11100011 #
b11100011 '
b11100011 %
#2280000
1!
0"
0(
1*
1+
b11100100 #
b11100100 '
b11100100 %
b101 &
#2290000
0!
1"
1(
0*
1)
b11100101 #
b11100101 '
b11100101 %
b100 &
#2300000
b11100110 #
b11100110 '
b11100110 %
b101 &
#2310000
1!
0"
0(
1*
0)
b11100111 #
b11100111 '
b11100111 %
#2320000
b11101000 #
b11101000 '
b11101000 %
b110 &
#2330000
0!
1"
1(
0*
1)
b11101001 #
b11101001 '
b11101001 %
b100 &
#2340000
b11101010 #
b11101010 '
b11101010 %
b101 &
#2350000
1!
0"
0(
1*
0)
b11101011 #
b11101011 '
b11101011 %
#2360000
0!
1"
1(
0*
0+
b11101100 #
b11101100 '
b11101100 %
b110 &
#2370000
1!
0"
0(
1*
1)
b11101101 #
b11101101 '
b11101101 %
b101 &
#2380000
b11101110 #
b11101110 '
b11101110 %
b110 &
#2390000
0!
1"
1(
0*
0)
b11101111 #
b11101111 '
b11101111 %
#2400000
1!
0"
0(
0-
0,
b11110000 #
b11110000 '
b11110000 %
b111 &
#2410000
0!
1"
1(
1*
1)
b11110001 #
b11110001 '
b11110001 %
b100 &
#2420000
b11110010 #
b11110010 '
b11110010 %
b101 &
#2430000
1!
0"
0(
0*
0)
b11110011 #
b11110011 '
b11110011 %
#2440000
0!
1"
1(
1*
1+
b11110100 #
b11110100 '
b11110100 %
b110 &
#2450000
1!
0"
0(
0*
1)
b11110101 #
b11110101 '
b11110101 %
b101 &
#2460000
b11110110 #
b11110110 '
b11110110 %
b110 &
#2470000
0!
1"
1(
1*
0)
b11110111 #
b11110111 '
b11110111 %
#2480000
b11111000 #
b11111000 '
b11111000 %
b111 &
#2490000
1!
0"
0(
0*
1)
b11111001 #
b11111001 '
b11111001 %
b101 &
#2500000
b11111010 #
b11111010 '
b11111010 %
b110 &
#2510000
0!
1"
1(
1*
0)
b11111011 #
b11111011 '
b11111011 %
#2520000
1!
0"
0(
0*
0+
b11111100 #
b11111100 '
b11111100 %
b111 &
#2530000
0!
1"
1(
1*
1)
b11111101 #
b11111101 '
b11111101 %
b110 &
#2540000
b11111110 #
b11111110 '
b11111110 %
b111 &
#2550000
1!
0"
0(
0*
0)
b11111111 #
b11111111 '
b11111111 %
#2560000
b100000000 %
b1000 &
