design/syndrome_decoder.sv
module syndrome_decoder (
    input wire [6:0] hamming_recibido,

    output wire [2:0] syndrome
);

    wire s1;
    wire s2;
    wire s4;

    // ==========================================
    // S1
    //
    // Posiciones:
    // 1, 3, 5, 7
    // ==========================================

    assign s1 =
        hamming_recibido[0] ^
        hamming_recibido[2] ^
        hamming_recibido[4] ^
        hamming_recibido[6];

    // ==========================================
    // S2
    //
    // Posiciones:
    // 2, 3, 6, 7
    // ==========================================

    assign s2 =
        hamming_recibido[1] ^
        hamming_recibido[2] ^
        hamming_recibido[5] ^
        hamming_recibido[6];

    // ==========================================
    // S4
    //
    // Posiciones:
    // 4, 5, 6, 7
    // ==========================================

    assign s4 =
        hamming_recibido[3] ^
        hamming_recibido[4] ^
        hamming_recibido[5] ^
        hamming_recibido[6];

    // ==========================================
    // SALIDA DEL SINDROME
    //
    // syndrome[2] = S4
    // syndrome[1] = S2
    // syndrome[0] = S1
    // ==========================================

    assign syndrome[2] = s4;
    assign syndrome[1] = s2;
    assign syndrome[0] = s1;

endmodule

sim/sim/tb_syndrome_decoder.sv
`timescale 1ns/1ps

module tb_syndrome_decoder;

    reg [6:0] hamming_recibido;

    wire [2:0] syndrome;

    syndrome_decoder dut (
        .hamming_recibido(hamming_recibido),
        .syndrome(syndrome)
    );

    initial begin

        $dumpfile("syndrome_decoder.vcd");
        $dumpvars(0, tb_syndrome_decoder);

        $display("==========================================");
        $display("TESTBENCH - DECODIFICADOR DE SINDROME");

        // ======================================
        // Sin error
        // ======================================

        hamming_recibido = 7'b0000000;
        #10;

        if (syndrome == 3'b000)
            $display("OK: 0000000 -> Sindrome 000");
        else
            $display("ERROR: 0000000");


        // ======================================
        // Error en posición 1
        // ======================================

        hamming_recibido = 7'b0000001;
        #10;

        if (syndrome == 3'b001)
            $display("OK: 0000001 -> Sindrome 001");
        else
            $display("ERROR: 0000001");


        // ======================================
        // Error en posición 2
        // ======================================

        hamming_recibido = 7'b0000010;
        #10;

        if (syndrome == 3'b010)
            $display("OK: 0000010 -> Sindrome 010");
        else
            $display("ERROR: 0000010");


        // ======================================
        // Error en posición 3
        // ======================================

        hamming_recibido = 7'b0000100;
        #10;

        if (syndrome == 3'b011)
            $display("OK: 0000100 -> Sindrome 011");
        else
            $display("ERROR: 0000100");


        // ======================================
        // Error en posición 4
        // ======================================

        hamming_recibido = 7'b0001000;
        #10;

        if (syndrome == 3'b100)
            $display("OK: 0001000 -> Sindrome 100");
        else
            $display("ERROR: 0001000");


        // ======================================
        // Error en posición 5
        // ======================================

        hamming_recibido = 7'b0010000;
        #10;

        if (syndrome == 3'b101)
            $display("OK: 0010000 -> Sindrome 101");
        else
            $display("ERROR: 0010000");


        // ======================================
        // Error en posición 6
        // ======================================

        hamming_recibido = 7'b0100000;
        #10;

        if (syndrome == 3'b110)
            $display("OK: 0100000 -> Sindrome 110");
        else
            $display("ERROR: 0100000");


        // ======================================
        // Error en posición 7
        // ======================================

        hamming_recibido = 7'b1000000;
        #10;

        if (syndrome == 3'b111)
            $display("OK: 1000000 -> Sindrome 111");
        else
            $display("ERROR: 1000000");


        $finish;

    end

endmodule

build/syndrome_decoder.vcd
$date
	Tue Sep 22 04:02:35 2026
$end
$version
	Icarus Verilog
$end
$timescale
	1ps
$end
$scope module tb_syndrome_decoder $end
$var wire 3 ! syndrome [2:0] $end
$var reg 7 " hamming_recibido [6:0] $end
$scope module dut $end
$var wire 7 # hamming_recibido [6:0] $end
$var wire 1 $ s1 $end
$var wire 1 % s2 $end
$var wire 1 & s4 $end
$var wire 3 ' syndrome [2:0] $end
$upscope $end
$upscope $end
$enddefinitions $end
$comment Show the parameter values. $end
$dumpall
$end
#0
$dumpvars
b0 '
0&
0%
0$
b0 #
b0 "
b0 !
$end
#10000
b1 !
b1 '
1$
b1 "
b1 #
#20000
0$
b10 !
b10 '
1%
b10 "
b10 #
#30000
b11 !
b11 '
1$
b100 "
b100 #
#40000
0$
0%
b100 !
b100 '
1&
b1000 "
b1000 #
#50000
b101 !
b101 '
1$
b10000 "
b10000 #
#60000
0$
1%
b110 !
b110 '
1&
b100000 "
b100000 #
#70000
1$
1%
b111 !
b111 '
1&
b1000000 "
b1000000 #
