design/display_decoder.sv
module display_decoder (
    input wire [6:0] palabra_corregida,
    input wire [2:0] syndrome,
    input wire ded,
    input wire switch_display,

    output wire [6:0] leds,
    output reg [6:0] segmentos
);

    reg [3:0] dato;
    reg [3:0] valor_display;

    // ==================================================
    // OBTENER LOS 4 BITS DE DATOS DEL HAMMING
    //
    // H1 H2 D1 H4 D2 D3 D4
    //
    // bit 0 = H1
    // bit 1 = H2
    // bit 2 = D1
    // bit 3 = H4
    // bit 4 = D2
    // bit 5 = D3
    // bit 6 = D4
    // ==================================================

    always @(*) begin

        dato[0] = palabra_corregida[2];
        dato[1] = palabra_corregida[4];
        dato[2] = palabra_corregida[5];
        dato[3] = palabra_corregida[6];

    end


    // ==================================================
    // SELECCIONAR QUE SE MUESTRA EN EL DISPLAY
    //
    // switch_display = 0 -> dato recibido
    // switch_display = 1 -> syndrome
    // ==================================================

    always @(*) begin

        if (switch_display == 1'b0)
            valor_display = dato;
        else
            valor_display = {1'b0, syndrome};

    end


    // ==================================================
    // DECODIFICADOR HEXADECIMAL
    //
    // segmentos[6:0] = G F E D C B A
    //
    // DISPLAY DE ANODO COMUN
    //
    // 0 = ENCENDIDO
    // 1 = APAGADO
    // ==================================================

    always @(*) begin

        case (valor_display)

            4'h0: segmentos = 7'b1000000;
            4'h1: segmentos = 7'b1111001;
            4'h2: segmentos = 7'b0100100;
            4'h3: segmentos = 7'b0110000;
            4'h4: segmentos = 7'b0011001;
            4'h5: segmentos = 7'b0010010;
            4'h6: segmentos = 7'b0000010;
            4'h7: segmentos = 7'b1111000;
            4'h8: segmentos = 7'b0000000;
            4'h9: segmentos = 7'b0010000;
            4'hA: segmentos = 7'b0001000;
            4'hB: segmentos = 7'b0000011;
            4'hC: segmentos = 7'b1000110;
            4'hD: segmentos = 7'b0100001;
            4'hE: segmentos = 7'b0000110;
            4'hF: segmentos = 7'b0001110;

            default:
                segmentos = 7'b1111111;

        endcase

    end


    // ==================================================
    // SALIDA DE LOS LEDS
    //
    // LED [0] = H1
    // LED [1] = H2
    // LED [2] = D1
    // LED [3] = H4
    // LED [4] = D2
    // LED [5] = D3
    // LED [6] = DED
    //
    // Los bits de paridad H1, H2 y H4 se muestran
    // apagados en esta visualización.
    // ==================================================

    assign leds = {
        ded,
        palabra_corregida[5],
        palabra_corregida[4],
        palabra_corregida[2],
        1'b0,
        1'b0,
        1'b0
    };

endmodule

sim/sim/tb_display_decoder.sv
`timescale 1ns/1ps

module tb_display_decoder;

    // ==========================================
    // ENTRADAS
    // ==========================================

    reg [6:0] palabra_corregida;
    reg [2:0] syndrome;
    reg ded;
    reg switch_display;

    // ==========================================
    // SALIDAS
    // ==========================================

    wire [6:0] leds;
    wire [6:0] segmentos;

    // ==========================================
    // VARIABLES DE PRUEBA
    // ==========================================

    integer hex_value;
    integer syndrome_value;
    integer switch_value;
    integer ded_value;

    integer pruebas;
    integer errores;

    reg [3:0] dato;
    reg [6:0] segmentos_esperados;
    reg [6:0] leds_esperados;


    // ==========================================
    // MODULO BAJO PRUEBA
    // ==========================================

    display_decoder DUT (
        .palabra_corregida(palabra_corregida),
        .syndrome(syndrome),
        .ded(ded),
        .switch_display(switch_display),
        .leds(leds),
        .segmentos(segmentos)
    );


    // ==========================================
    // VALORES ESPERADOS DEL DISPLAY
    //
    // segmentos[6:0] = G F E D C B A
    //
    // DISPLAY DE ANODO COMUN
    //
    // 0 = ENCENDIDO
    // 1 = APAGADO
    // ==========================================

    function [6:0] segmentos_hex;

        input [3:0] valor;

        begin

            case (valor)

                4'h0: segmentos_hex = 7'b1000000;
                4'h1: segmentos_hex = 7'b1111001;
                4'h2: segmentos_hex = 7'b0100100;
                4'h3: segmentos_hex = 7'b0110000;
                4'h4: segmentos_hex = 7'b0011001;
                4'h5: segmentos_hex = 7'b0010010;
                4'h6: segmentos_hex = 7'b0000010;
                4'h7: segmentos_hex = 7'b1111000;
                4'h8: segmentos_hex = 7'b0000000;
                4'h9: segmentos_hex = 7'b0010000;
                4'hA: segmentos_hex = 7'b0001000;
                4'hB: segmentos_hex = 7'b0000011;
                4'hC: segmentos_hex = 7'b1000110;
                4'hD: segmentos_hex = 7'b0100001;
                4'hE: segmentos_hex = 7'b0000110;
                4'hF: segmentos_hex = 7'b0001110;

                default:
                    segmentos_hex = 7'b1111111;

            endcase

        end

    endfunction


    // ==========================================
    // INICIO DE LA SIMULACION
    // ==========================================

    initial begin

        pruebas = 0;
        errores = 0;

        palabra_corregida = 7'b0000000;
        syndrome = 3'b000;
        ded = 1'b0;
        switch_display = 1'b0;

        #10;




        // ==================================================
        // PRUEBA 1
        // 16 VALORES HEXADECIMALES
        // SWITCH = 0
        // DED = 0
        // ==================================================

        $display("-----------------------------------------------");
        $display("PRUEBA 1: VALORES HEXADECIMALES");
        $display("-----------------------------------------------");

        for (hex_value = 0;
             hex_value < 16;
             hex_value = hex_value + 1) begin

            dato = hex_value;

            // ------------------------------------------
            // Construir palabra Hamming
            //
            // H1 H2 D1 H4 D2 D3 D4
            //
            // bit 0 = H1
            // bit 1 = H2
            // bit 2 = D1
            // bit 3 = H4
            // bit 4 = D2
            // bit 5 = D3
            // bit 6 = D4
            // ------------------------------------------

            palabra_corregida[0] = 1'b0;
            palabra_corregida[1] = 1'b0;

            palabra_corregida[2] = dato[0];

            palabra_corregida[3] = 1'b0;

            palabra_corregida[4] = dato[1];
            palabra_corregida[5] = dato[2];
            palabra_corregida[6] = dato[3];

            syndrome = 3'b000;
            switch_display = 1'b0;
            ded = 1'b0;

            #1;

            segmentos_esperados = segmentos_hex(dato);

            pruebas = pruebas + 1;

            if (segmentos !== segmentos_esperados) begin

                errores = errores + 1;

                $display(
                    "ERROR HEX %h | Esperado=%b | Obtenido=%b",
                    dato,
                    segmentos_esperados,
                    segmentos
                );

            end
            else begin

                $display(
                    "OK HEX %h | Segmentos=%b",
                    dato,
                    segmentos
                );

            end

        end



        // ==================================================
        // PRUEBA 2
        // 8 SINDROMES
        // SWITCH = 1
        // DED = 0
        // ==================================================

        $display("");
        $display("-----------------------------------------------");
        $display("PRUEBA 2: 8 SINDROMES");
        $display("-----------------------------------------------");

        for (syndrome_value = 0;
             syndrome_value < 8;
             syndrome_value = syndrome_value + 1) begin

            syndrome = syndrome_value;

            switch_display = 1'b1;

            ded = 1'b0;

            palabra_corregida = 7'b0000000;

            #1;

            segmentos_esperados =
                segmentos_hex(syndrome_value);

            pruebas = pruebas + 1;

            if (segmentos !== segmentos_esperados) begin

                errores = errores + 1;

                $display(
                    "ERROR SYNDROME %03b | Esperado=%b | Obtenido=%b",
                    syndrome,
                    segmentos_esperados,
                    segmentos
                );

            end
            else begin

                $display(
                    "OK SYNDROME %03b | Segmentos=%b",
                    syndrome,
                    segmentos
                );

            end

        end



        // ==================================================
        // PRUEBA 3
        // AMBOS ESTADOS DEL SWITCH
        //
        // Se utiliza un mismo dato y un síndrome
        // diferente para comprobar que realmente
        // cambia lo mostrado.
        // ==================================================

        $display("");
        $display("-----------------------------------------------");
        $display("PRUEBA 3: SWITCH OFF / ON");
        $display("-----------------------------------------------");


        // ------------------------------------------
        // DATO = A
        // SYNDROME = 5
        // ------------------------------------------

        dato = 4'hA;

        palabra_corregida[0] = 1'b0;
        palabra_corregida[1] = 1'b0;
        palabra_corregida[2] = dato[0];
        palabra_corregida[3] = 1'b0;
        palabra_corregida[4] = dato[1];
        palabra_corregida[5] = dato[2];
        palabra_corregida[6] = dato[3];

        syndrome = 3'b101;

        ded = 1'b0;


        // ------------------------------------------
        // SWITCH = 0
        // Debe mostrar A
        // ------------------------------------------

        switch_display = 1'b0;

        #1;

        segmentos_esperados = segmentos_hex(4'hA);

        pruebas = pruebas + 1;

        if (segmentos !== segmentos_esperados) begin

            errores = errores + 1;

            $display(
                "ERROR SWITCH=0 | Esperado A | Obtenido=%b",
                segmentos
            );

        end
        else begin

            $display(
                "OK SWITCH=0 | Mostrando A | %b",
                segmentos
            );

        end


        // ------------------------------------------
        // SWITCH = 1
        // Debe mostrar 5
        // ------------------------------------------

        switch_display = 1'b1;

        #1;

        segmentos_esperados = segmentos_hex(4'h5);

        pruebas = pruebas + 1;

        if (segmentos !== segmentos_esperados) begin

            errores = errores + 1;

            $display(
                "ERROR SWITCH=1 | Esperado 5 | Obtenido=%b",
                segmentos
            );

        end
        else begin

            $display(
                "OK SWITCH=1 | Mostrando 5 | %b",
                segmentos
            );

        end



        // ==================================================
        // PRUEBA 4
        // DED = 0
        // ==================================================

        $display("");
        $display("-----------------------------------------------");
        $display("PRUEBA 4: DED = 0");
        $display("-----------------------------------------------");

        ded = 1'b0;

        #1;

        pruebas = pruebas + 1;

        if (leds[6] !== 1'b0) begin

            errores = errores + 1;

            $display(
                "ERROR DED=0 | LED DED esperado=0 | obtenido=%b",
                leds[6]
            );

        end
        else begin

            $display(
                "OK DED=0 | LED DED=%b",
                leds[6]
            );

        end



        // ==================================================
        // PRUEBA 5
        // DED = 1
        // ==================================================

        $display("");
        $display("-----------------------------------------------");
        $display("PRUEBA 5: DED = 1");
        $display("-----------------------------------------------");

        ded = 1'b1;

        #1;

        pruebas = pruebas + 1;

        if (leds[6] !== 1'b1) begin

            errores = errores + 1;

            $display(
                "ERROR DED=1 | LED DED esperado=1 | obtenido=%b",
                leds[6]
            );

        end
        else begin

            $display(
                "OK DED=1 | LED DED=%b",
                leds[6]
            );

        end



        // ==================================================
        // PRUEBA 6
        // COMPROBAR LOS 7 LEDS
        // ==================================================

        $display("");
        $display("-----------------------------------------------");
        $display("PRUEBA 6: LEDS DE LA FPGA");
        $display("-----------------------------------------------");

        palabra_corregida = 7'b1010101;

        ded = 1'b0;

        switch_display = 1'b0;

        #1;

        leds_esperados = 7'b0010101;

        pruebas = pruebas + 1;

        if (leds !== leds_esperados) begin

            errores = errores + 1;

            $display(
                "ERROR LEDS | Esperado=%b | Obtenido=%b",
                leds_esperados,
                leds
            );

        end
        else begin

            $display(
                "OK LEDS | Valor=%b",
                leds
            );

        end



        // ==================================================
        // PRUEBA 7
        // DED CON DIFERENTES VALORES
        // ==================================================

        $display("");
        $display("-----------------------------------------------");
        $display("PRUEBA 7: DED CON LOS DOS ESTADOS");
        $display("-----------------------------------------------");


        for (ded_value = 0;
             ded_value < 2;
             ded_value = ded_value + 1) begin

            ded = ded_value;

            #1;

            pruebas = pruebas + 1;

            if (leds[6] !== ded) begin

                errores = errores + 1;

                $display(
                    "ERROR DED=%b | LED=%b",
                    ded,
                    leds[6]
                );

            end
            else begin

                $display(
                    "OK DED=%b | LED=%b",
                    ded,
                    leds[6]
                );

            end

        end



        // ==================================================
        // RESULTADO FINAL
        // ==================================================

        $display("");
        $display("================================================");
        $display(" RESULTADO FINAL");
        $display("================================================");

        $display(
            "Cantidad de pruebas: %0d",
            pruebas
        );

        $display(
            "Cantidad de errores: %0d",
            errores
        );

        $display("");


        if (errores == 0) begin

            $display("****************************************");
            $display("*Pasaron*");
            $display("****************************************");

        end
        else begin

            $display("****************************************");
            $display("* SE ENCONTRARON ERRORES               *");
            $display("****************************************");

        end

        $display("");

        $finish;

    end



    // ==================================================
    // GENERAR ARCHIVO VCD
    // ==================================================

    initial begin

        $dumpfile("tb_display_decoder.vcd");

        $dumpvars(0, tb_display_decoder);

    end

endmodule

build/tb_display_decoder.vcd
$date
	Tue Sep 22 04:02:52 2026
$end
$version
	Icarus Verilog
$end
$timescale
	1ps
$end
$scope module tb_display_decoder $end
$var wire 7 ! segmentos [6:0] $end
$var wire 7 " leds [6:0] $end
$var reg 4 # dato [3:0] $end
$var reg 1 $ ded $end
$var reg 7 % leds_esperados [6:0] $end
$var reg 7 & palabra_corregida [6:0] $end
$var reg 7 ' segmentos_esperados [6:0] $end
$var reg 1 ( switch_display $end
$var reg 3 ) syndrome [2:0] $end
$var integer 32 * ded_value [31:0] $end
$var integer 32 + errores [31:0] $end
$var integer 32 , hex_value [31:0] $end
$var integer 32 - pruebas [31:0] $end
$var integer 32 . syndrome_value [31:0] $end
$scope function segmentos_hex $end
$var reg 4 / valor [3:0] $end
$upscope $end
$scope module DUT $end
$var wire 1 $ ded $end
$var wire 7 0 palabra_corregida [6:0] $end
$var wire 1 ( switch_display $end
$var wire 3 1 syndrome [2:0] $end
$var wire 7 2 leds [6:0] $end
$var reg 4 3 dato [3:0] $end
$var reg 7 4 segmentos [6:0] $end
$var reg 4 5 valor_display [3:0] $end
$upscope $end
$upscope $end
$enddefinitions $end
$comment Show the parameter values. $end
$dumpall
$end
#0
$dumpvars
b0 5
b1000000 4
b0 3
b0 2
b0 1
b0 0
bx /
bx .
b0 -
bx ,
b0 +
bx *
b0 )
0(
bx '
b0 &
bx %
0$
bx #
b0 "
b1000000 !
$end
#10000
b0 #
b0 ,
#11000
b1111001 !
b1111001 4
b1 5
b1 3
b1000 "
b1000 2
b100 &
b100 0
b1 #
b1 ,
b1 -
b1000000 '
b0 /
#12000
b100100 !
b100100 4
b10 5
b10 3
b10000 "
b10000 2
b10000 &
b10000 0
b10 #
b10 ,
b10 -
b1111001 '
b1 /
#13000
b110000 !
b110000 4
b11 5
b11 3
b11000 "
b11000 2
b10100 &
b10100 0
b11 #
b11 ,
b11 -
b100100 '
b10 /
#14000
b11001 !
b11001 4
b100 5
b100 3
b100000 "
b100000 2
b100000 &
b100000 0
b100 #
b100 ,
b100 -
b110000 '
b11 /
#15000
b10010 !
b10010 4
b101 5
b101 3
b101000 "
b101000 2
b100100 &
b100100 0
b101 #
b101 ,
b101 -
b11001 '
b100 /
#16000
b10 !
b10 4
b110 5
b110 3
b110000 "
b110000 2
b110000 &
b110000 0
b110 #
b110 ,
b110 -
b10010 '
b101 /
#17000
b1111000 !
b1111000 4
b111 5
b111 3
b111000 "
b111000 2
b110100 &
b110100 0
b111 #
b111 ,
b111 -
b10 '
b110 /
#18000
b0 !
b0 4
b1000 5
b1000 3
b0 "
b0 2
b1000000 &
b1000000 0
b1000 #
b1000 ,
b1000 -
b1111000 '
b111 /
#19000
b10000 !
b10000 4
b1001 5
b1001 3
b1000 "
b1000 2
b1000100 &
b1000100 0
b1001 #
b1001 ,
b1001 -
b0 '
b1000 /
#20000
b1000 !
b1000 4
b1010 5
b1010 3
b10000 "
b10000 2
b1010000 &
b1010000 0
b1010 #
b1010 ,
b1010 -
b10000 '
b1001 /
#21000
b11 !
b11 4
b1011 5
b1011 3
b11000 "
b11000 2
b1010100 &
b1010100 0
b1011 #
b1011 ,
b1011 -
b1000 '
b1010 /
#22000
b1000110 !
b1000110 4
b1100 5
b1100 3
b100000 "
b100000 2
b1100000 &
b1100000 0
b1100 #
b1100 ,
b1100 -
b11 '
b1011 /
#23000
b100001 !
b100001 4
b1101 5
b1101 3
b101000 "
b101000 2
b1100100 &
b1100100 0
b1101 #
b1101 ,
b1101 -
b1000110 '
b1100 /
#24000
b110 !
b110 4
b1110 5
b1110 3
b110000 "
b110000 2
b1110000 &
b1110000 0
b1110 #
b1110 ,
b1110 -
b100001 '
b1101 /
#25000
b1110 !
b1110 4
b1111 5
b1111 3
b111000 "
b111000 2
b1110100 &
b1110100 0
b1111 #
b1111 ,
b1111 -
b110 '
b1110 /
#26000
b1000000 !
b1000000 4
b0 3
b0 "
b0 2
b0 5
b0 &
b0 0
1(
b0 .
b10000 ,
b10000 -
b1110 '
b1111 /
#27000
b1111001 !
b1111001 4
b1 5
b1 )
b1 1
b1 .
b10001 -
b1000000 '
b0 /
#28000
b100100 !
b100100 4
b10 5
b10 )
b10 1
b10 .
b10010 -
b1111001 '
b1 /
#29000
b110000 !
b110000 4
b11 5
b11 )
b11 1
b11 .
b10011 -
b100100 '
b10 /
#30000
b11001 !
b11001 4
b100 5
b100 )
b100 1
b100 .
b10100 -
b110000 '
b11 /
#31000
b10010 !
b10010 4
b101 5
b101 )
b101 1
b101 .
b10101 -
b11001 '
b100 /
#32000
b10 !
b10 4
b110 5
b110 )
b110 1
b110 .
b10110 -
b10010 '
b101 /
#33000
b1111000 !
b1111000 4
b111 5
b111 )
b111 1
b111 .
b10111 -
b10 '
b110 /
#34000
b1000 !
b1000 4
b1010 5
b1010 3
b10000 "
b10000 2
0(
b101 )
b101 1
b1010000 &
b1010000 0
b1010 #
b1000 .
b11000 -
b1111000 '
b111 /
#35000
b10010 !
b10010 4
b101 5
1(
b11001 -
b1000 '
b1010 /
#36000
b11010 -
b10010 '
b101 /
#37000
b1010000 "
b1010000 2
1$
b11011 -
#38000
b11 !
b11 4
b1011 5
b1011 3
0(
b11000 "
b11000 2
0$
b1010101 &
b1010101 0
b11100 -
#39000
b0 *
b1 +
b11101 -
b10101 %
#40000
b1011000 "
b1011000 2
1$
b1 *
b11110 -
#41000
b10 *
b11111 -
